{"code":"ACA","name":"Air Canada","id":1,"name":"Toronto","id":1,"street":"1325 Canterburry Lane","city":"Westminster","province_state":"Colorado","postal_code":"80007","country_code":"1"}
{"code":"ACA","name":"Air Canada","id":2,"name":"Montreal","id":1,"street":"1325 Canterburry Lane","city":"Westminster","province_state":"Colorado","postal_code":"80007","country_code":"1"}
{"code":"ACA","name":"Air Canada","id":3,"name":"Chicago","id":1,"street":"1325 Canterburry Lane","city":"Westminster","province_state":"Colorado","postal_code":"80007","country_code":"1"}
{"code":"ACA","name":"Air Canada","id":4,"name":"New York","id":1,"street":"1325 Canterburry Lane","city":"Westminster","province_state":"Colorado","postal_code":"80007","country_code":"1"}
{"code":"ACA","name":"Air Canada","id":5,"name":"London","id":1,"street":"1325 Canterburry Lane","city":"Westminster","province_state":"Colorado","postal_code":"80007","country_code":"1"}
{"code":"ACA","name":"Air Canada","id":6,"name":"Edinnburgh","id":1,"street":"1325 Canterburry Lane","city":"Westminster","province_state":"Colorado","postal_code":"80007","country_code":"1"}
{"code":"ACA","name":"Air Canada","id":7,"name":"Nice","id":1,"street":"1325 Canterburry Lane","city":"Westminster","province_state":"Colorado","postal_code":"80007","country_code":"1"}
{"code":"ACA","name":"Air Canada","id":8,"name":"France","id":1,"street":"1325 Canterburry Lane","city":"Westminster","province_state":"Colorado","postal_code":"80007","country_code":"1"}
{"code":"UAL","name":"United Airlines","id":1,"name":"Toronto","id":1,"street":"1325 Canterburry Lane","city":"Westminster","province_state":"Colorado","postal_code":"80007","country_code":"1"}
{"code":"UAL","name":"United Airlines","id":2,"name":"Montreal","id":1,"street":"1325 Canterburry Lane","city":"Westminster","province_state":"Colorado","postal_code":"80007","country_code":"1"}
{"code":"UAL","name":"United Airlines","id":3,"name":"Chicago","id":1,"street":"1325 Canterburry Lane","city":"Westminster","province_state":"Colorado","postal_code":"80007","country_code":"1"}
{"code":"UAL","name":"United Airlines","id":4,"name":"New York","id":1,"street":"1325 Canterburry Lane","city":"Westminster","province_state":"Colorado","postal_code":"80007","country_code":"1"}
{"code":"UAL","name":"United Airlines","id":5,"name":"London","id":1,"street":"1325 Canterburry Lane","city":"Westminster","province_state":"Colorado","postal_code":"80007","country_code":"1"}
{"code":"UAL","name":"United Airlines","id":6,"name":"Edinnburgh","id":1,"street":"1325 Canterburry Lane","city":"Westminster","province_state":"Colorado","postal_code":"80007","country_code":"1"}
{"code":"UAL","name":"United Airlines","id":7,"name":"Nice","id":1,"street":"1325 Canterburry Lane","city":"Westminster","province_state":"Colorado","postal_code":"80007","country_code":"1"}
{"code":"UAL","name":"United Airlines","id":8,"name":"France","id":1,"street":"1325 Canterburry Lane","city":"Westminster","province_state":"Colorado","postal_code":"80007","country_code":"1"}
{"code":"BAW","name":"British Airways","id":1,"name":"Toronto","id":1,"street":"1325 Canterburry Lane","city":"Westminster","province_state":"Colorado","postal_code":"80007","country_code":"1"}
{"code":"BAW","name":"British Airways","id":2,"name":"Montreal","id":1,"street":"1325 Canterburry Lane","city":"Westminster","province_state":"Colorado","postal_code":"80007","country_code":"1"}
{"code":"BAW","name":"British Airways","id":3,"name":"Chicago","id":1,"street":"1325 Canterburry Lane","city":"Westminster","province_state":"Colorado","postal_code":"80007","country_code":"1"}
{"code":"BAW","name":"British Airways","id":4,"name":"New York","id":1,"street":"1325 Canterburry Lane","city":"Westminster","province_state":"Colorado","postal_code":"80007","country_code":"1"}
{"code":"BAW","name":"British Airways","id":5,"name":"London","id":1,"street":"1325 Canterburry Lane","city":"Westminster","province_state":"Colorado","postal_code":"80007","country_code":"1"}
{"code":"BAW","name":"British Airways","id":6,"name":"Edinnburgh","id":1,"street":"1325 Canterburry Lane","city":"Westminster","province_state":"Colorado","postal_code":"80007","country_code":"1"}
{"code":"BAW","name":"British Airways","id":7,"name":"Nice","id":1,"street":"1325 Canterburry Lane","city":"Westminster","province_state":"Colorado","postal_code":"80007","country_code":"1"}
{"code":"BAW","name":"British Airways","id":8,"name":"France","id":1,"street":"1325 Canterburry Lane","city":"Westminster","province_state":"Colorado","postal_code":"80007","country_code":"1"}
